injectinput/__init__.py
injectinput/injectinput.py
injectinput-0.3.0.dist-info/METADATA
injectinput-0.3.0.dist-info/WHEEL
injectinput-0.3.0.dist-info/entry_points.txt
injectinput-0.3.0.dist-info/RECORD
