Metadata-Version: 2.1
Name: injectinput
Version: 0.3.0
Summary: Inject input
License: GPL-3.0
Author: Dick Marinus
Author-email: dick@mrns.nl
Requires-Python: >=3.8
Classifier: License :: OSI Approved :: GNU General Public License v3 (GPLv3)
Classifier: Programming Language :: Python :: 3
Classifier: Programming Language :: Python :: 3.8
Classifier: Programming Language :: Python :: 3.9
Classifier: Programming Language :: Python :: 3.10
Classifier: Programming Language :: Python :: 3.11
Classifier: Programming Language :: Python :: 3.12
Requires-Dist: evdev (>=1.6.1)
